covvvr/__init__.py
covvvr/_cvitime.py
covvvr/_exceptions.py
covvvr/_types.py
covvvr/_wrappers.py
covvvr/cvintegrator.py
covvvr/functions.py
covvvr-1.4.1.dist-info/LICENSE
covvvr-1.4.1.dist-info/METADATA
covvvr-1.4.1.dist-info/WHEEL
covvvr-1.4.1.dist-info/top_level.txt
covvvr-1.4.1.dist-info/RECORD
